mfd_package_manager/__init__.py
mfd_package_manager/base.py
mfd_package_manager/bsd.py
mfd_package_manager/const.py
mfd_package_manager/data_structures.py
mfd_package_manager/esxi.py
mfd_package_manager/exceptions.py
mfd_package_manager/linux.py
mfd_package_manager/unix.py
mfd_package_manager/windows.py
mfd_package_manager-3.0.0.dist-info/licenses/AUTHORS.md
mfd_package_manager-3.0.0.dist-info/licenses/LICENSE.md
mfd_package_manager-3.0.0.dist-info/METADATA
mfd_package_manager-3.0.0.dist-info/WHEEL
mfd_package_manager-3.0.0.dist-info/top_level.txt
mfd_package_manager-3.0.0.dist-info/RECORD
