Metadata-Version: 2.4
Name: mfd-package-manager
Version: 3.0.0
Summary: Module for managing packages, drivers, and modules across Linux, Windows, ESXi, and FreeBSD systems.
Project-URL: Homepage, https://github.com/intel/mfd
Project-URL: Repository, https://github.com/intel/mfd-package-manager
Project-URL: Issues, https://github.com/intel/mfd-package-manager/issues
Project-URL: Changelog, https://github.com/intel/mfd-package-manager/blob/main/CHANGELOG.md
Requires-Python: <3.14,>=3.10
License-File: LICENSE.md
License-File: AUTHORS.md
Requires-Dist: mfd-typing>=1.23.0
Requires-Dist: mfd-connect>=7.12
Requires-Dist: mfd-sysctl>=1.6.0
Requires-Dist: mfd-devcon>=2.0.0
Requires-Dist: mfd-const>=0.23.0
Requires-Dist: mfd-ethtool>=3.14.0
Requires-Dist: mfd-win-registry>=1.17.0
Dynamic: license-file
